linefinder/__init__.py
linefinder/classify.py
linefinder/config.py
linefinder/galaxy_link.py
linefinder/linefinder.py
linefinder/select.py
linefinder/track.py
linefinder/visualize.py
linefinder/analyze_data/__init__.py
linefinder/analyze_data/classifications.py
linefinder/analyze_data/events.py
linefinder/analyze_data/galids.py
linefinder/analyze_data/ids.py
linefinder/analyze_data/plot_worldlines.py
linefinder/analyze_data/ptracks.py
linefinder/analyze_data/worldline_set.py
linefinder/analyze_data/worldlines.py
linefinder/job_scripts/__init__.py
linefinder/job_scripts/linefinder_CGM_trove_jugfile.py
linefinder/job_scripts/linefinder_CGM_trove_jugfile_copy.py
linefinder/job_scripts/linefinder_clustersofFIRE.py
linefinder/job_scripts/linefinder_example.py
linefinder/job_scripts/linefinder_ismsquare.py
linefinder/job_scripts/linefinder_m83clusters.py
linefinder/job_scripts/linefinder_rockstar.py
linefinder/job_scripts/linefinder_sightlines.py
linefinder/job_scripts/linefinder_trove.py
linefinder/job_scripts/linefinder_trove_jugfile.py
linefinder/job_scripts/run_classify.py
linefinder/job_scripts/run_select.py
linefinder/tests/__init__.py
linefinder/tests/conftest.py
linefinder/tests/find_galaxies_for_ptracks_jugfile.py
linefinder/tests/linefinder_jugfile.py
linefinder/tests/select_jugfile.py
linefinder/tests/test_classify.py
linefinder/tests/test_full_pipeline.py
linefinder/tests/test_galaxy_link.py
linefinder/tests/test_select.py
linefinder/tests/test_track.py
linefinder/tests/track_jugfile.py
linefinder/utils/__init__.py
linefinder/utils/file_management.py
linefinder/utils/pathfinder_CGM_trove_jugfile.py
linefinder/utils/presentation_constants.py
linefinder/utils/trove_management.py
linefinder-0.9.3.dist-info/LICENSE
linefinder-0.9.3.dist-info/METADATA
linefinder-0.9.3.dist-info/WHEEL
linefinder-0.9.3.dist-info/top_level.txt
linefinder-0.9.3.dist-info/RECORD
